crawler/__init__.py
dircrawler/__init__.py
fscrawler/__init__.py
dircrawler-0.0.2.dist-info/LICENSE.txt
dircrawler-0.0.2.dist-info/METADATA
dircrawler-0.0.2.dist-info/WHEEL
dircrawler-0.0.2.dist-info/top_level.txt
dircrawler-0.0.2.dist-info/RECORD
