Metadata-Version: 2.1
Name: dircrawler
Version: 0.0.2
Summary: General purpose crawler
Home-page: UNKNOWN
Author: mhaisham
Author-email: mhaisham79@gmail.com
License: UNKNOWN
Platform: UNKNOWN
Requires-Python: >=3.6
